moark_comfyui_engine.cpython-310-x86_64-linux-gnu.so
moark_comfyui_engine.pyi
moark_comfyui_engine-0.1.0.dist-info/METADATA
moark_comfyui_engine-0.1.0.dist-info/WHEEL
moark_comfyui_engine-0.1.0.dist-info/top_level.txt
moark_comfyui_engine-0.1.0.dist-info/RECORD
