Metadata-Version: 2.4
Name: moark_comfyui_engine
Version: 0.1.0
Summary: ComfyUI engine modules
Author: Moark
Author-email: support@moark.com
License: Apache-2.0
Requires-Dist: bentoml==1.4.26
Dynamic: author
Dynamic: author-email
Dynamic: license
Dynamic: requires-dist
Dynamic: summary
